ghmd/__init__.py
ghmd/__main__.py
ghmd/md-template.html
behsareport-0.4.0.dist-info/METADATA
behsareport-0.4.0.dist-info/WHEEL
behsareport-0.4.0.dist-info/entry_points.txt
behsareport-0.4.0.dist-info/top_level.txt
behsareport-0.4.0.dist-info/RECORD
