Metadata-Version: 2.4
Name: behsareport
Version: 0.4.0
Summary: A simple CLI to convert markdown files to HTML using GitHub API using the GitHub Markdown style.
Author-email: Arian Ebrahimi <ae@arianebrahimni.ir>
Project-URL: Homepage, https://github.com/ariianebrahiimii/ghmd
Project-URL: Repository, https://github.com/ariianebrahiimii/ghmd.git
Project-URL: Changelog, https://github.com/ariianebrahiimii/ghmd/blob/main/CHANGELOG.md
Keywords: markdown,github,cli,html,converter
Classifier: License :: OSI Approved :: MIT License
Classifier: Intended Audience :: End Users/Desktop
Classifier: Intended Audience :: Developers
Classifier: Topic :: Software Development :: Build Tools
Classifier: Topic :: Text Processing :: Markup :: HTML
Classifier: Programming Language :: Python
Classifier: Programming Language :: Python :: 3
Classifier: Programming Language :: Python :: 3.6
Classifier: Programming Language :: Python :: 3.7
Classifier: Programming Language :: Python :: 3.8
Classifier: Programming Language :: Python :: 3.9
Classifier: Programming Language :: Python :: 3.10
Classifier: Programming Language :: Python :: 3.11
Classifier: Programming Language :: Python :: 3.12
Classifier: Programming Language :: Python :: 3.13
Classifier: Programming Language :: Python :: 3.14
Requires-Python: >=3.6
Requires-Dist: jdatetime>=3.8.2
Requires-Dist: requests
